yolo_circle_sdk/__init__.py
yolo_circle_sdk/api.py
yolo_circle_sdk/cli.py
yolo_circle_sdk/config.py
yolo_circle_sdk/detector.py
yolo_circle_sdk/model_manager.py
yolo_circle_sdk/models/best1.pt
yolo_circle_sdk-1.0.2.dist-info/METADATA
yolo_circle_sdk-1.0.2.dist-info/WHEEL
yolo_circle_sdk-1.0.2.dist-info/entry_points.txt
yolo_circle_sdk-1.0.2.dist-info/top_level.txt
yolo_circle_sdk-1.0.2.dist-info/RECORD
